wfmeta_dask/__init__.py
wfmeta_dask/__main__.py
wfmeta_dask/helpers.py
wfmeta_dask/objs/__init__.py
wfmeta_dask/objs/enums.py
wfmeta_dask/objs/events.py
wfmeta_dask/objs/tasks.py
wfmeta_dask-1.0.0.dist-info/licenses/LICENSE
wfmeta_dask-1.0.0.dist-info/METADATA
wfmeta_dask-1.0.0.dist-info/WHEEL
wfmeta_dask-1.0.0.dist-info/entry_points.txt
wfmeta_dask-1.0.0.dist-info/top_level.txt
wfmeta_dask-1.0.0.dist-info/RECORD
