Metadata-Version: 2.4
Name: wfmeta_dask
Version: 1.0.0
Summary: wfmeta Tool to parse and restructure the scheduler and worker event logs captured by the dask-mofka plugin.
Author-email: Polina Shpilker <infinite.loopholes@gmail.com>
License-Expression: MIT
Project-URL: Homepage, https://github.com/RECUP-DOE/wfmeta-dask
Requires-Python: >=3.12
License-File: LICENSE
Requires-Dist: numpy>1.24.4
Requires-Dist: pandas>=2.0.3
Dynamic: license-file
